cyfgame/__init__.py
cyfgame/image.py
cyfgame/key.py
cyfgame/sound.py
tests/__init__.py
tests/test_image.py
cyfgame-0.1.0.dist-info/LICENSE
cyfgame-0.1.0.dist-info/METADATA
cyfgame-0.1.0.dist-info/WHEEL
cyfgame-0.1.0.dist-info/top_level.txt
cyfgame-0.1.0.dist-info/RECORD
