Metadata-Version: 2.1
Name: cyfgame
Version: 0.1.0
Summary: Give you a better programming experience to play games.
Home-page: UNKNOWN
Author: cyf
Author-email: chengyf1314@qq.com
License: UNKNOWN
Platform: UNKNOWN
Classifier: Programming Language :: Python :: 3
Classifier: License :: OSI Approved :: MIT License
Classifier: Operating System :: OS Independent
Requires-Dist: pygame
